u3dunpack/AssetsManager.py
u3dunpack/__init__.py
u3dunpack/engine/AssetBundle.py
u3dunpack/engine/EditorExtension.py
u3dunpack/engine/GLTextureSettings.py
u3dunpack/engine/GameObject.py
u3dunpack/engine/NamedObject.py
u3dunpack/engine/Object.py
u3dunpack/engine/PPtr.py
u3dunpack/engine/StreamingInfo.py
u3dunpack/engine/Texture.py
u3dunpack/engine/Texture2D.py
u3dunpack/engine/__init__.py
u3dunpack/enums/BuildTarget.py
u3dunpack/enums/ClassIDType.py
u3dunpack/enums/CommonString.py
u3dunpack/enums/FileType.py
u3dunpack/enums/TextureFormat.py
u3dunpack/enums/UnityType.py
u3dunpack/enums/__init__.py
u3dunpack/export/KtxConverter.py
u3dunpack/export/Texture2DConverter.py
u3dunpack/export/__init__.py
u3dunpack/file/BlockInfo.py
u3dunpack/file/BuildType.py
u3dunpack/file/BundleFile.py
u3dunpack/file/ResourcesFile.py
u3dunpack/file/__init__.py
u3dunpack/file/serialized/FileIdentifier.py
u3dunpack/file/serialized/LocalSerializedObjectIdentifier.py
u3dunpack/file/serialized/ObjectReader.py
u3dunpack/file/serialized/SerializedFile.py
u3dunpack/file/serialized/SerializedFileHeader.py
u3dunpack/file/serialized/SerializedType.py
u3dunpack/file/serialized/TypeTreeNode.py
u3dunpack/file/serialized/__init__.py
u3dunpack/streams/EndianBinaryReader.py
u3dunpack/streams/EndianBinaryWriter.py
u3dunpack/streams/__init__.py
u3dunpack/utils/ImportUtils.py
u3dunpack/utils/KtxUtils.py
u3dunpack/utils/Lz4Utils.py
u3dunpack/utils/LzmaUtils.py
u3dunpack/utils/ResourceReader.py
u3dunpack/utils/SerializedUtils.py
u3dunpack/utils/TypeTreeUtils.py
u3dunpack/utils/UnityUtils.py
u3dunpack/utils/__init__.py
u3dunpack/writer/ResourceConverter.py
u3dunpack/writer/__init__.py
u3d_studio-1.0.16.dist-info/LICENSE
u3d_studio-1.0.16.dist-info/METADATA
u3d_studio-1.0.16.dist-info/WHEEL
u3d_studio-1.0.16.dist-info/top_level.txt
u3d_studio-1.0.16.dist-info/RECORD
