Metadata-Version: 2.1
Name: u3d-studio
Version: 1.0.16
Summary: a python library for u3d unpacking
Home-page: https://github.com/smalls0098/u3d-assets-tools
Author: smalls
Author-email: smalls0098@gmail.com
License: UNKNOWN
Download-URL: https://github.com/smalls0098/u3d-assets-tools/tarball/master
Keywords: u3dpack,unitypack,u3d-assets-tools,assetspack
Platform: UNKNOWN
Classifier: License :: OSI Approved :: MIT License
Classifier: Operating System :: OS Independent
Classifier: Intended Audience :: Developers
Classifier: License :: OSI Approved :: MIT License
Classifier: Topic :: Multimedia :: Graphics
Classifier: Programming Language :: Python :: 3.6
Classifier: Programming Language :: Python :: 3.7
Classifier: Programming Language :: Python :: 3.8
Requires-Dist: lz4
Requires-Dist: Pillow
Requires-Dist: tex2img
